pz_uniconfig/Uniconfig.py
pz_uniconfig/__init__.py
pz_uniconfig/utilities.py
pz_uniconfig/exceptions/__init__.py
pz_uniconfig/exceptions/config_format_error.py
pz_uniconfig/parser/__init__.py
pz_uniconfig/parser/dotenv_parser.py
pz_uniconfig/parser/ini_parser.py
pz_uniconfig/parser/json_parser.py
pz_uniconfig/parser/toml_parser.py
pz_uniconfig/parser/yaml_parser.py
pz_uniconfig-1.0.1.dist-info/METADATA
pz_uniconfig-1.0.1.dist-info/WHEEL
pz_uniconfig-1.0.1.dist-info/licenses/LICENSE
pz_uniconfig-1.0.1.dist-info/RECORD
