Metadata-Version: 2.4
Name: pz-uniconfig
Version: 1.0.1
Summary: Unified config management for Python: YAML, JSON, TOML, dotenv, INI—one API.
Project-URL: Homepage, https://github.com/poziel/uniconfig
Project-URL: Issues, https://github.com/poziel/uniconfig
Author-email: Alexandre Sauvé <alexandre.sauve.dev@gmail.com>
License-File: LICENSE
Classifier: License :: OSI Approved :: MIT License
Classifier: Operating System :: OS Independent
Classifier: Programming Language :: Python :: 3
Requires-Python: >=3.0
Requires-Dist: dotenv~=0.9.9
Requires-Dist: python-dotenv~=1.1.0
Requires-Dist: pyyaml~=6.0.2
Requires-Dist: requests
Requires-Dist: sqlalchemy
Requires-Dist: toml~=0.10.2
Provides-Extra: test
Requires-Dist: docutils; extra == 'test'
Requires-Dist: pytest~=8.3.5; extra == 'test'
